wkhtmltopdf/__init__.py
wkhtmltopdf/models.py
wkhtmltopdf/subprocess.py
wkhtmltopdf/utils.py
wkhtmltopdf/views.py
wkhtmltopdf/tests/__init__.py
wkhtmltopdf/tests/models.py
wkhtmltopdf/tests/run.py
wkhtmltopdf/tests/tests.py
wkhtmltopdf/tests/templates/context.html
wkhtmltopdf/tests/templates/footer.html
wkhtmltopdf/tests/templates/sample.html
wkhtmltopdf/tests/templates/unicode.html
django_wkhtmltopdf-3.4.0.dist-info/LICENSE
django_wkhtmltopdf-3.4.0.dist-info/METADATA
django_wkhtmltopdf-3.4.0.dist-info/WHEEL
django_wkhtmltopdf-3.4.0.dist-info/top_level.txt
django_wkhtmltopdf-3.4.0.dist-info/RECORD
