Metadata-Version: 1.1
Name: django-wkhtmltopdf
Version: 3.4.0
Summary: Converts HTML to PDF using wkhtmltopdf.
Home-page: https://github.com/incuna/django-wkhtmltopdf
Author: Incuna Ltd
Author-email: admin@incuna.com
License: BSD-2-Clause
Keywords: django wkhtmltopdf pdf
Platform: UNKNOWN
Classifier: Development Status :: 5 - Production/Stable
Classifier: Environment :: Web Environment
Classifier: Intended Audience :: Developers
Classifier: Operating System :: OS Independent
Classifier: License :: OSI Approved :: MIT License
Classifier: Programming Language :: Python :: 2
Classifier: Programming Language :: Python :: 2.6
Classifier: Programming Language :: Python :: 2.7
Classifier: Programming Language :: Python :: 3
Classifier: Programming Language :: Python :: 3.3
Classifier: Programming Language :: Python :: 3.4
Classifier: Framework :: Django
